cogee/__init__.py
cogee/cogee.py
cogee-1.0.2.dist-info/LICENSE
cogee-1.0.2.dist-info/METADATA
cogee-1.0.2.dist-info/WHEEL
cogee-1.0.2.dist-info/entry_points.txt
cogee-1.0.2.dist-info/top_level.txt
cogee-1.0.2.dist-info/RECORD
