Metadata-Version: 2.1
Name: cogee
Version: 1.0.2
Summary: COG EE flow
Home-page: https://github.com/samapriya/cogee
Author: Samapriya Roy
Author-email: samapriya.roy@gmail.com
License: Apache 2.0
Classifier: Development Status :: 4 - Beta
Classifier: Intended Audience :: Developers
Classifier: Intended Audience :: Science/Research
Classifier: Natural Language :: English
Classifier: License :: OSI Approved :: Apache Software License
Classifier: Programming Language :: Python :: 3
Classifier: Programming Language :: Python :: 3.6
Classifier: Programming Language :: Python :: 3.7
Classifier: Programming Language :: Python :: 3.8
Classifier: Programming Language :: Python :: 3.9
Classifier: Operating System :: OS Independent
Classifier: Topic :: Scientific/Engineering :: GIS
License-File: LICENSE
Requires-Dist: earthengine-api >=0.1.367
Requires-Dist: requests >=2.22.0
Requires-Dist: beautifulsoup4 >=4.9.0
